nvflare/__init__.py
nvflare/poc.zip
nvflare/apis/__init__.py
nvflare/apis/analytix.py
nvflare/apis/app_validation.py
nvflare/apis/aux_spec.py
nvflare/apis/client.py
nvflare/apis/client_engine_spec.py
nvflare/apis/controller_spec.py
nvflare/apis/dxo.py
nvflare/apis/event_type.py
nvflare/apis/executor.py
nvflare/apis/filter.py
nvflare/apis/fl_component.py
nvflare/apis/fl_constant.py
nvflare/apis/fl_context.py
nvflare/apis/fl_exception.py
nvflare/apis/responder.py
nvflare/apis/server_engine_spec.py
nvflare/apis/shareable.py
nvflare/apis/signal.py
nvflare/apis/workspace.py
nvflare/apis/impl/__init__.py
nvflare/apis/impl/any_relay_manager.py
nvflare/apis/impl/bcast_manager.py
nvflare/apis/impl/controller.py
nvflare/apis/impl/send_manager.py
nvflare/apis/impl/seq_relay_manager.py
nvflare/apis/impl/task_manager.py
nvflare/apis/utils/__init__.py
nvflare/apis/utils/fl_context_utils.py
nvflare/apis/utils/format_check.py
nvflare/app_common/__init__.py
nvflare/app_common/app_constant.py
nvflare/app_common/app_event_type.py
nvflare/app_common/model_desc.py
nvflare/app_common/abstract/__init__.py
nvflare/app_common/abstract/aggregator.py
nvflare/app_common/abstract/formatter.py
nvflare/app_common/abstract/learnable.py
nvflare/app_common/abstract/learnable_persistor.py
nvflare/app_common/abstract/learner_spec.py
nvflare/app_common/abstract/model.py
nvflare/app_common/abstract/model_locator.py
nvflare/app_common/abstract/model_persistor.py
nvflare/app_common/abstract/model_processor.py
nvflare/app_common/abstract/shareable_generator.py
nvflare/app_common/aggregators/__init__.py
nvflare/app_common/aggregators/accumulate_model_aggregator.py
nvflare/app_common/aggregators/intime_accumulate_model_aggregator.py
nvflare/app_common/executors/__init__.py
nvflare/app_common/executors/learner_executor.py
nvflare/app_common/executors/multi_process_executor.py
nvflare/app_common/filters/__init__.py
nvflare/app_common/filters/convert_weights.py
nvflare/app_common/filters/exclude_vars.py
nvflare_nightly-1.1.0.dev211220.dist-info/LICENSE
nvflare_nightly-1.1.0.dev211220.dist-info/METADATA
nvflare_nightly-1.1.0.dev211220.dist-info/WHEEL
nvflare_nightly-1.1.0.dev211220.dist-info/entry_points.txt
nvflare_nightly-1.1.0.dev211220.dist-info/top_level.txt
nvflare_nightly-1.1.0.dev211220.dist-info/zip-safe
nvflare_nightly-1.1.0.dev211220.dist-info/RECORD
