Metadata-Version: 2.1
Name: nvflare-nightly
Version: 1.1.0.dev211220
Summary: Federated Learning Application Runtime Environment
Home-page: https://github.com/NVIDIA/NVFlare
License: UNKNOWN
Platform: UNKNOWN
Classifier: Programming Language :: Python :: 3
Classifier: License :: Other/Proprietary License
Classifier: Operating System :: OS Independent
Requires-Python: >=3.8
Requires-Dist: PyYAML
Requires-Dist: psutil
Requires-Dist: numpy
Requires-Dist: grpcio
Requires-Dist: google-api-python-client
Requires-Dist: cryptography
Requires-Dist: tenseal (==0.3.0)
